{
    "description": "Your past favorites",
    "num_followers": 0,
    "original_name": "Repeat Rewind",
    "owner": {
        "name": "Spotify",
        "url": "https://open.spotify.com/user/spotify"
    },
    "snapshot_id": "ZoId+QAAAABXbPDakRieGsDAt3rnAzt7",
    "tracks": [
        {
            "added_at": "2024-07-01 03:09:45",
            "album": {
                "name": "When The Summer Dies",
                "url": "https://open.spotify.com/album/7LasafuTdmSWgVvC1Zweum"
            },
            "artists": [
                {
                    "name": "deadmau5",
                    "url": "https://open.spotify.com/artist/2CIMQHirSU0MQqyYHq0eOx"
                },
                {
                    "name": "Lights",
                    "url": "https://open.spotify.com/artist/5pdyjBIaY5o1yOyexGIUc6"
                }
            ],
            "duration_ms": 329531,
            "name": "When The Summer Dies",
            "url": "https://open.spotify.com/track/1Lgvs8WzpPbT5VuUFIAJwt"
        },
        {
            "added_at": "2024-07-01 03:09:45",
            "album": {
                "name": "Prada (feat. D-Block Europe) [Valexus Remix]",
                "url": "https://open.spotify.com/album/1kmVDYAYMwrVavfO1PYC6q"
            },
            "artists": [
                {
                    "name": "cassö",
                    "url": "https://open.spotify.com/artist/5wCmhq5J2hPwL2r0eKurxn"
                },
                {
                    "name": "RAYE",
                    "url": "https://open.spotify.com/artist/5KKpBU5eC2tJDzf0wmlRp2"
                },
                {
                    "name": "Valexus",
                    "url": "https://open.spotify.com/artist/7bzKgx8PQw6TCVDSD43pc1"
                },
                {
                    "name": "D-Block Europe",
                    "url": "https://open.spotify.com/artist/5VadK1havLhK1OpKYsXv9y"
                }
            ],
            "duration_ms": 135125,
            "name": "Prada (feat. D-Block Europe) - Valexus Remix",
            "url": "https://open.spotify.com/track/1hmI7H4W0ChPH6vfa9i2CQ"
        },
        {
            "added_at": "2024-07-01 03:09:45",
            "album": {
                "name": "Badlapur (Original Motion Picture Soundtrack)",
                "url": "https://open.spotify.com/album/4ahg47diWPOQ6d6C8e6PHI"
            },
            "artists": [
                {
                    "name": "Atif Aslam",
                    "url": "https://open.spotify.com/artist/2oSONSC9zQ4UonDKnLqksx"
                }
            ],
            "duration_ms": 228969,
            "name": "Jeena Jeena",
            "url": "https://open.spotify.com/track/2GXXZFUxYg2LvG8SR0byOE"
        },
        {
            "added_at": "2024-07-01 03:09:45",
            "album": {
                "name": "Tarantella",
                "url": "https://open.spotify.com/album/0nxNoLQWFwsRqTfLh7R0sq"
            },
            "artists": [
                {
                    "name": "Gabry Ponte",
                    "url": "https://open.spotify.com/artist/5ENS85nZShljwNgg4wFD7D"
                },
                {
                    "name": "KEL",
                    "url": "https://open.spotify.com/artist/7tYjk2vuV96DmlpEHLlw05"
                }
            ],
            "duration_ms": 145553,
            "name": "Tarantella",
            "url": "https://open.spotify.com/track/4pBuhoBxgwBpkkOhfT6p6N"
        },
        {
            "added_at": "2024-07-01 03:09:45",
            "album": {
                "name": "Rule The World",
                "url": "https://open.spotify.com/album/4tgL0C4pYRxpNLde755TFr"
            },
            "artists": [
                {
                    "name": "GAMPER & DADONI",
                    "url": "https://open.spotify.com/artist/6HQ6vf4AloXyVNdyJhrX1J"
                },
                {
                    "name": "ILIRA",
                    "url": "https://open.spotify.com/artist/6mzs66iVW15C5iLt0JLt41"
                }
            ],
            "duration_ms": 170785,
            "name": "Rule The World",
            "url": "https://open.spotify.com/track/22sKunNSPMCy2lvSLOY5yX"
        },
        {
            "added_at": "2024-07-01 03:09:45",
            "album": {
                "name": "We Will Rave",
                "url": "https://open.spotify.com/album/4nNMa36op8YViMSJQXgWLl"
            },
            "artists": [
                {
                    "name": "Kaleen",
                    "url": "https://open.spotify.com/artist/6c2Y3AYl05QMPbLMCGag6P"
                }
            ],
            "duration_ms": 185066,
            "name": "We Will Rave",
            "url": "https://open.spotify.com/track/1QpWQMKfQ44QUN1dEg65T8"
        },
        {
            "added_at": "2024-07-01 03:09:45",
            "album": {
                "name": "Best of Romance: Atif Aslam & Pritam",
                "url": "https://open.spotify.com/album/3vDIjYB1eatEoGlVoZWUFs"
            },
            "artists": [
                {
                    "name": "Atif Aslam",
                    "url": "https://open.spotify.com/artist/2oSONSC9zQ4UonDKnLqksx"
                },
                {
                    "name": "Pritam",
                    "url": "https://open.spotify.com/artist/1wRPtKGflJrBx9BmLsSwlU"
                }
            ],
            "duration_ms": 312892,
            "name": "Pehli Nazar Mein",
            "url": "https://open.spotify.com/track/5llaVhaIoowKT3fqf2NfPO"
        },
        {
            "added_at": "2024-07-01 03:09:45",
            "album": {
                "name": "Crying On The Dancefloor",
                "url": "https://open.spotify.com/album/4IUv9dcdWGXkug84xuIwX7"
            },
            "artists": [
                {
                    "name": "Sam Feldt",
                    "url": "https://open.spotify.com/artist/20gsENnposVs2I4rQ5kvrf"
                },
                {
                    "name": "Jonas Blue",
                    "url": "https://open.spotify.com/artist/1HBjj22wzbscIZ9sEb5dyf"
                },
                {
                    "name": "Endless Summer",
                    "url": "https://open.spotify.com/artist/3E0d6yF8knEtWluzLbxCVA"
                },
                {
                    "name": "Violet Days",
                    "url": "https://open.spotify.com/artist/4uNv6RD2YXwoaKgHfJZkkL"
                }
            ],
            "duration_ms": 173008,
            "name": "Crying On The Dancefloor",
            "url": "https://open.spotify.com/track/09rAJ1Q1NNJSaUKEW3X9P6"
        },
        {
            "added_at": "2024-07-01 03:09:45",
            "album": {
                "name": "EURODANCER 2020",
                "url": "https://open.spotify.com/album/0mhRA2LPy9Peh9DQqov78D"
            },
            "artists": [
                {
                    "name": "Mangoo",
                    "url": "https://open.spotify.com/artist/6ObeGN1qTsep95QRNOfNc3"
                },
                {
                    "name": "Dimatik",
                    "url": "https://open.spotify.com/artist/2Zvo5BEkHyaHD1zk180kMz"
                }
            ],
            "duration_ms": 132963,
            "name": "EURODANCER 2020",
            "url": "https://open.spotify.com/track/4hSm8pkwQCrIVgUET79zwy"
        },
        {
            "added_at": "2024-07-01 03:09:45",
            "album": {
                "name": "Happiness",
                "url": "https://open.spotify.com/album/7bioTTAoIfJDKndK4fITTt"
            },
            "artists": [
                {
                    "name": "Tomcraft",
                    "url": "https://open.spotify.com/artist/2E4lzxgBnCEqLawsXeRKWp"
                },
                {
                    "name": "MOGUAI",
                    "url": "https://open.spotify.com/artist/4xgFgBZ7CRtgtHcziClOwQ"
                },
                {
                    "name": "ILIRA",
                    "url": "https://open.spotify.com/artist/6mzs66iVW15C5iLt0JLt41"
                }
            ],
            "duration_ms": 150486,
            "name": "Happiness",
            "url": "https://open.spotify.com/track/7IgA0pcFcslMMsBZsDnWaX"
        },
        {
            "added_at": "2024-07-01 03:09:45",
            "album": {
                "name": "Right Now (Remix)",
                "url": "https://open.spotify.com/album/2cHLiYIGBgcttWX2Ekf6zb"
            },
            "artists": [
                {
                    "name": "Guilherme Arraes",
                    "url": "https://open.spotify.com/artist/72S4gZDeo46Cqjh58fRoo8"
                },
                {
                    "name": "VISIONARE",
                    "url": "https://open.spotify.com/artist/1crOVABMVKHRzLkHZZ1zUD"
                },
                {
                    "name": "VELLØN",
                    "url": "https://open.spotify.com/artist/2PEhrnVwCz5xeFTvs9GsIo"
                }
            ],
            "duration_ms": 99613,
            "name": "Right Now (Remix)",
            "url": "https://open.spotify.com/track/4ixpcIQTt7EE1EAqotGZGb"
        },
        {
            "added_at": "2024-07-01 03:09:45",
            "album": {
                "name": "Dynamite",
                "url": "https://open.spotify.com/album/3PclTvUZ12jHy1bmWecbuW"
            },
            "artists": [
                {
                    "name": "ILIRA",
                    "url": "https://open.spotify.com/artist/6mzs66iVW15C5iLt0JLt41"
                },
                {
                    "name": "VIZE",
                    "url": "https://open.spotify.com/artist/09agIJMxCD2k87ys9Al0f0"
                }
            ],
            "duration_ms": 125878,
            "name": "Dynamite",
            "url": "https://open.spotify.com/track/3HqQpSTLHJRKDhulVacRFb"
        },
        {
            "added_at": "2024-07-01 03:09:45",
            "album": {
                "name": "Infinity (feat. ILIRA, iiola & Tom Cane)",
                "url": "https://open.spotify.com/album/4X2i68rMNDVwGMTeXW5bek"
            },
            "artists": [
                {
                    "name": "Wilkinson",
                    "url": "https://open.spotify.com/artist/6m8itYST9ADjBIYevXSb1r"
                },
                {
                    "name": "ILIRA",
                    "url": "https://open.spotify.com/artist/6mzs66iVW15C5iLt0JLt41"
                },
                {
                    "name": "iiola",
                    "url": "https://open.spotify.com/artist/3YSLjtLPCULe41kgElVrWj"
                },
                {
                    "name": "Tom Cane",
                    "url": "https://open.spotify.com/artist/5iFDzfBI6aebgrb9ljJhme"
                }
            ],
            "duration_ms": 213793,
            "name": "Infinity (feat. ILIRA, iiola & Tom Cane)",
            "url": "https://open.spotify.com/track/0CkmD2L3xMeZTXOwlOCsVm"
        },
        {
            "added_at": "2024-07-01 03:09:45",
            "album": {
                "name": "UAG",
                "url": "https://open.spotify.com/album/6xko2pJwfeUJFMma9it2wH"
            },
            "artists": [
                {
                    "name": "Umur Anil Gokdag",
                    "url": "https://open.spotify.com/artist/6TE5uKxtwtgJ2kcUNRhzJP"
                }
            ],
            "duration_ms": 128369,
            "name": "Somewhere Only We Know",
            "url": "https://open.spotify.com/track/3ZdonRSIema00XbpqGWVLJ"
        },
        {
            "added_at": "2024-07-01 03:09:45",
            "album": {
                "name": "Anytime",
                "url": "https://open.spotify.com/album/6eDNIUfe63AsdaFw3R4abu"
            },
            "artists": [
                {
                    "name": "Phil The Beat",
                    "url": "https://open.spotify.com/artist/35pKZ36ma78w8aE467fRO9"
                },
                {
                    "name": "ILIRA",
                    "url": "https://open.spotify.com/artist/6mzs66iVW15C5iLt0JLt41"
                }
            ],
            "duration_ms": 148500,
            "name": "Anytime",
            "url": "https://open.spotify.com/track/4pAxG2OEh4LSNuZFzDRUbN"
        },
        {
            "added_at": "2024-07-01 03:09:45",
            "album": {
                "name": "Fartaqi",
                "url": "https://open.spotify.com/album/46y3eqKg2y5IceTGROJi6T"
            },
            "artists": [
                {
                    "name": "Ahmed Bukhatir",
                    "url": "https://open.spotify.com/artist/7H045XjM40okitH2R60OrR"
                }
            ],
            "duration_ms": 240586,
            "name": "Ya Adheeman",
            "url": "https://open.spotify.com/track/5MNrC9YlvHVkHiiCfZnNSt"
        },
        {
            "added_at": "2024-07-01 03:09:45",
            "album": {
                "name": "Alien",
                "url": "https://open.spotify.com/album/7hLrEkGfc02E0ckMf3MEGh"
            },
            "artists": [
                {
                    "name": "Galantis",
                    "url": "https://open.spotify.com/artist/4sTQVOfp9vEMCemLw50sbu"
                },
                {
                    "name": "Lucas & Steve",
                    "url": "https://open.spotify.com/artist/5wwneIFdawNgQ7GvKK29Z3"
                },
                {
                    "name": "ILIRA",
                    "url": "https://open.spotify.com/artist/6mzs66iVW15C5iLt0JLt41"
                }
            ],
            "duration_ms": 165858,
            "name": "Alien",
            "url": "https://open.spotify.com/track/6VBLbFCArFuTTEXFlQFZZs"
        },
        {
            "added_at": "2024-07-01 03:09:45",
            "album": {
                "name": "Are You OK? (feat. ILIRA)",
                "url": "https://open.spotify.com/album/6CXKk17m3VB5S08HGPdTTJ"
            },
            "artists": [
                {
                    "name": "Yves V",
                    "url": "https://open.spotify.com/artist/47BEc2RoW53owMyxacXWdV"
                },
                {
                    "name": "Dubdogz",
                    "url": "https://open.spotify.com/artist/4cdyqaBREB68H77QKCrKP1"
                },
                {
                    "name": "ILIRA",
                    "url": "https://open.spotify.com/artist/6mzs66iVW15C5iLt0JLt41"
                }
            ],
            "duration_ms": 148624,
            "name": "Are You OK? (feat. ILIRA)",
            "url": "https://open.spotify.com/track/6Ppext7tYrK3trnspkoSry"
        },
        {
            "added_at": "2024-07-01 03:09:45",
            "album": {
                "name": "Sticker on My Suitcase",
                "url": "https://open.spotify.com/album/6qCYObNjXCIDrW3MBXTWLy"
            },
            "artists": [
                {
                    "name": "Alle Farben",
                    "url": "https://open.spotify.com/artist/61ipISvUVa5LkJlKZnm3Oo"
                },
                {
                    "name": "ILIRA",
                    "url": "https://open.spotify.com/artist/6mzs66iVW15C5iLt0JLt41"
                }
            ],
            "duration_ms": 206373,
            "name": "Fading",
            "url": "https://open.spotify.com/track/2WyNqDHLRJLzJuidCsO1Ey"
        },
        {
            "added_at": "2024-07-01 03:09:45",
            "album": {
                "name": "Rich In Love",
                "url": "https://open.spotify.com/album/1ZJuNaxvUtHns8WCpIaAh9"
            },
            "artists": [
                {
                    "name": "SUPER-Hi",
                    "url": "https://open.spotify.com/artist/2lJ6K4PTrrweXhRiqh1CZE"
                },
                {
                    "name": "ILIRA",
                    "url": "https://open.spotify.com/artist/6mzs66iVW15C5iLt0JLt41"
                }
            ],
            "duration_ms": 205186,
            "name": "Rich In Love",
            "url": "https://open.spotify.com/track/424bdPXDmsR1WgZoCUwxt4"
        },
        {
            "added_at": "2024-07-01 03:09:45",
            "album": {
                "name": "Best of Us",
                "url": "https://open.spotify.com/album/5The4yrlGj0HOZJbiLixt4"
            },
            "artists": [
                {
                    "name": "WIER",
                    "url": "https://open.spotify.com/artist/2eGAHWide96MItPXtwxMr2"
                },
                {
                    "name": "Alexa Feser",
                    "url": "https://open.spotify.com/artist/0Yb66lSgYL9MFYw6jUHCVD"
                },
                {
                    "name": "Annett Louisan",
                    "url": "https://open.spotify.com/artist/0kcGSitPHYyZ9B7bP7wJo8"
                },
                {
                    "name": "Bibi Bourelly",
                    "url": "https://open.spotify.com/artist/3jDtqAKltRxJi64svLZGj7"
                },
                {
                    "name": "Christina Stürmer",
                    "url": "https://open.spotify.com/artist/5GnRHCbhnGp57tp4whNvOo"
                },
                {
                    "name": "Conor Byrne",
                    "url": "https://open.spotify.com/artist/0hEeBhTVYUKs2B4PY2IdMB"
                },
                {
                    "name": "Glasperlenspiel",
                    "url": "https://open.spotify.com/artist/2UFKXTZgKtOTHSqMSyAcLO"
                },
                {
                    "name": "ILIRA",
                    "url": "https://open.spotify.com/artist/6mzs66iVW15C5iLt0JLt41"
                },
                {
                    "name": "Joel Brandenstein",
                    "url": "https://open.spotify.com/artist/0VUeSHZjbneQ8Ti7whkL9A"
                },
                {
                    "name": "JORIS",
                    "url": "https://open.spotify.com/artist/7BKePXVmQRgnkbGcrFX1G4"
                },
                {
                    "name": "Justin Jesso",
                    "url": "https://open.spotify.com/artist/1QDrz3DMMaz3TB1cm0PGDu"
                },
                {
                    "name": "KAYEF",
                    "url": "https://open.spotify.com/artist/4hXT6A14n901v8DU5Of337"
                },
                {
                    "name": "Kelvin Jones",
                    "url": "https://open.spotify.com/artist/2t1vHqFELDwweQWM6JYxHG"
                },
                {
                    "name": "LOTTE",
                    "url": "https://open.spotify.com/artist/3gqabzO7zvHVzAIT0Nxqa3"
                },
                {
                    "name": "Milow",
                    "url": "https://open.spotify.com/artist/6mo0UbyIvIePdXNyLwQlk5"
                },
                {
                    "name": "Nico Santos",
                    "url": "https://open.spotify.com/artist/3A9B6c1CrSPauiOblw7pWz"
                },
                {
                    "name": "Philipp Dittberner",
                    "url": "https://open.spotify.com/artist/7oaSITFPadI3fnIxbv7hTa"
                },
                {
                    "name": "Sasha",
                    "url": "https://open.spotify.com/artist/091dY4SjI2cy4YHdvhCjg1"
                },
                {
                    "name": "Stefanie Heinzmann",
                    "url": "https://open.spotify.com/artist/0bm9qSmVJmT9CEukIhhZY5"
                }
            ],
            "duration_ms": 197250,
            "name": "Best of Us",
            "url": "https://open.spotify.com/track/5DhcEJWVdkPNkJUVnbiUKo"
        },
        {
            "added_at": "2024-07-01 03:09:45",
            "album": {
                "name": "Weekend (Party, Sleep, Repeat)",
                "url": "https://open.spotify.com/album/2rBpiaXs2GC7mPr6ckxfi3"
            },
            "artists": [
                {
                    "name": "Mark Mendy",
                    "url": "https://open.spotify.com/artist/7AgS2ycsLUG0NPTY1AAboT"
                },
                {
                    "name": "Paradigm",
                    "url": "https://open.spotify.com/artist/6WamMeXO2jN9tUYxSBUclQ"
                }
            ],
            "duration_ms": 138556,
            "name": "Weekend (Party, Sleep, Repeat)",
            "url": "https://open.spotify.com/track/5066WzFaeJhqmQmKjBmrr6"
        },
        {
            "added_at": "2024-07-01 03:09:45",
            "album": {
                "name": "Ladida (My Heart Goes Boom)",
                "url": "https://open.spotify.com/album/2HpmiktvXy9VwEt3dzgC6Z"
            },
            "artists": [
                {
                    "name": "Kool Kat",
                    "url": "https://open.spotify.com/artist/2ay7u2zX2O4CheUsUNC4EU"
                },
                {
                    "name": "ILIRA",
                    "url": "https://open.spotify.com/artist/6mzs66iVW15C5iLt0JLt41"
                }
            ],
            "duration_ms": 173333,
            "name": "Ladida (My Heart Goes Boom)",
            "url": "https://open.spotify.com/track/5oJa785dEiK3F16gBeWeqf"
        },
        {
            "added_at": "2024-07-01 03:09:45",
            "album": {
                "name": "YRF Top 10 - Falling in Love",
                "url": "https://open.spotify.com/album/1ujIERX0vWqw9kcYr6VMRp"
            },
            "artists": [
                {
                    "name": "Atif Aslam",
                    "url": "https://open.spotify.com/artist/2oSONSC9zQ4UonDKnLqksx"
                }
            ],
            "duration_ms": 260536,
            "name": "Dil Diyan Gallan",
            "url": "https://open.spotify.com/track/0FBQ4NrrHUbR9kus7rzrOj"
        },
        {
            "added_at": "2024-07-01 03:09:45",
            "album": {
                "name": "ACID",
                "url": "https://open.spotify.com/album/7LAUJxkEQOBf6rbS0MXUi6"
            },
            "artists": [
                {
                    "name": "Hardwell",
                    "url": "https://open.spotify.com/artist/6BrvowZBreEkXzJQMpL174"
                },
                {
                    "name": "Maddix",
                    "url": "https://open.spotify.com/artist/0RMeG9M8QFzss9bAbq99KA"
                },
                {
                    "name": "Luciana",
                    "url": "https://open.spotify.com/artist/4ugGMtXC28CVR5hlYJy9wV"
                }
            ],
            "duration_ms": 181333,
            "name": "ACID",
            "url": "https://open.spotify.com/track/6JkQb1qCCJDBV7kW5vJUAH"
        },
        {
            "added_at": "2024-07-01 03:09:45",
            "album": {
                "name": "Heaven (feat. Sofia Quinn) [Club Mix]",
                "url": "https://open.spotify.com/album/3Vw0qrLB2KLYTXEPRFVK9b"
            },
            "artists": [
                {
                    "name": "Fedde Le Grand",
                    "url": "https://open.spotify.com/artist/7dc6hUwyuIhrZdh80eaCEE"
                },
                {
                    "name": "Robert Falcon",
                    "url": "https://open.spotify.com/artist/5CVwY7MrkxGF1aM4f1u6Xk"
                },
                {
                    "name": "Sofia Quinn",
                    "url": "https://open.spotify.com/artist/7aa9NIJCeJoYtpUL56UH6Q"
                }
            ],
            "duration_ms": 175773,
            "name": "Heaven (feat. Sofia Quinn) - Club Mix",
            "url": "https://open.spotify.com/track/6uTCim4OGFZOauCqHWIpu9"
        },
        {
            "added_at": "2024-07-01 03:09:45",
            "album": {
                "name": "With The Music I Die (Deluxe)",
                "url": "https://open.spotify.com/album/6lTavhbKfE9Fy582VHOCv4"
            },
            "artists": [
                {
                    "name": "Wynter Gordon",
                    "url": "https://open.spotify.com/artist/4nmrm4zpgJ0RC6aZRSUEjF"
                }
            ],
            "duration_ms": 197586,
            "name": "Dirty Talk",
            "url": "https://open.spotify.com/track/0MX8RxbgtZWRGZRE0Z6zNS"
        },
        {
            "added_at": "2024-07-01 03:09:45",
            "album": {
                "name": "Can't Go Back",
                "url": "https://open.spotify.com/album/4m9Hbf4YgKLLXDCDAyAR3K"
            },
            "artists": [
                {
                    "name": "Kouss",
                    "url": "https://open.spotify.com/artist/7nepWph1tZT5bw2aL4DEci"
                },
                {
                    "name": "Anna Kline",
                    "url": "https://open.spotify.com/artist/2J0XuKu0MDIR0XtxZkAbDo"
                }
            ],
            "duration_ms": 210000,
            "name": "Can't Go Back",
            "url": "https://open.spotify.com/track/5SHi8JgPkLA6f5WV7skTL5"
        },
        {
            "added_at": "2024-07-01 03:09:45",
            "album": {
                "name": "Sushi",
                "url": "https://open.spotify.com/album/7LUvu9YDD8yIom5z4yeSdt"
            },
            "artists": [
                {
                    "name": "MOTi",
                    "url": "https://open.spotify.com/artist/1vo8zHmO1KzkuU9Xxh6J7W"
                },
                {
                    "name": "ILIRA",
                    "url": "https://open.spotify.com/artist/6mzs66iVW15C5iLt0JLt41"
                }
            ],
            "duration_ms": 137708,
            "name": "Sushi",
            "url": "https://open.spotify.com/track/2kMSfE03xa0kyksSNIfufy"
        },
        {
            "added_at": "2024-07-01 03:09:45",
            "album": {
                "name": "ROYALTY",
                "url": "https://open.spotify.com/album/4N0qELFCNm3QsePKYSC9zZ"
            },
            "artists": [
                {
                    "name": "ILIRA",
                    "url": "https://open.spotify.com/artist/6mzs66iVW15C5iLt0JLt41"
                }
            ],
            "duration_ms": 165120,
            "name": "ROYALTY",
            "url": "https://open.spotify.com/track/35Tfg1o4XVqAxbUFXd3jp5"
        }
    ],
    "unique_name": "Repeat Rewind",
    "url": "https://open.spotify.com/playlist/37i9dQZF1EpSWsemYCkpY3"
}
