{
    "description": "<a href=spotify:playlist:37i9dQZF1EIXUVDweJ4wAc>framed</a>, <a href=spotify:playlist:37i9dQZF1EIZijMaKYYMzE>Little Richard</a>, <a href=spotify:playlist:37i9dQZF1EIZKt8Jk2STWz>Jerry Lee Lewis</a> and more",
    "num_followers": 0,
    "original_name": "50s Mix",
    "owner": {
        "name": "Spotify",
        "url": "https://open.spotify.com/user/spotify"
    },
    "snapshot_id": "MTY4ODc5NjAwMCwwMDAwMDAwMDJhNzQzMjIzOWMyNWUyNDYzYjZhMTkxYzA0ZWViYzBm",
    "tracks": [
        {
            "added_at": null,
            "album": {
                "name": "Uhh",
                "url": "https://open.spotify.com/album/3PgoWZSSEFdI0f5gektpdn"
            },
            "artists": [
                {
                    "name": "framed",
                    "url": "https://open.spotify.com/artist/6qW2MCeqjNlMwiLl0JPbuZ"
                }
            ],
            "duration_ms": 83947,
            "name": "uhh",
            "url": "https://open.spotify.com/track/3iDQnloxYVrnzE0eNZ85en"
        },
        {
            "added_at": null,
            "album": {
                "name": "Here's Little Richard (Deluxe Edition)",
                "url": "https://open.spotify.com/album/18tV6PLXYvVjsdOVk0S7M8"
            },
            "artists": [
                {
                    "name": "Little Richard",
                    "url": "https://open.spotify.com/artist/4xls23Ye9WR9yy3yYMpAMm"
                }
            ],
            "duration_ms": 144226,
            "name": "Tutti Frutti",
            "url": "https://open.spotify.com/track/2iXcvnD3d1gfLBum0cE5Eg"
        },
        {
            "added_at": null,
            "album": {
                "name": "Jerry Lee's Greatest",
                "url": "https://open.spotify.com/album/02FCCye8QsWyjHwedg9Quj"
            },
            "artists": [
                {
                    "name": "Jerry Lee Lewis",
                    "url": "https://open.spotify.com/artist/2zyz0VJqrDXeFDIyrfVXSo"
                }
            ],
            "duration_ms": 111535,
            "name": "Great Balls Of Fire",
            "url": "https://open.spotify.com/track/64VP3skE86iTvdOlbzuIcO"
        },
        {
            "added_at": null,
            "album": {
                "name": "Where Have You Been",
                "url": "https://open.spotify.com/album/3oSqZFuo4Xo5nQHgOYq7sL"
            },
            "artists": [
                {
                    "name": "Ren0wned",
                    "url": "https://open.spotify.com/artist/0U9UOUZ2iSmDR1tBe7F7tt"
                }
            ],
            "duration_ms": 208941,
            "name": "Where Have You Been - Sped Up",
            "url": "https://open.spotify.com/track/60H3RKGYQi1p5e8lPNaylT"
        },
        {
            "added_at": null,
            "album": {
                "name": "Asli Naqli",
                "url": "https://open.spotify.com/album/0Bl5C3tHLLJBWpDx8dO4Fv"
            },
            "artists": [
                {
                    "name": "Lata Mangeshkar",
                    "url": "https://open.spotify.com/artist/61JrslREXq98hurYL2hYoc"
                }
            ],
            "duration_ms": 190960,
            "name": "Tera Mera Pyar Amar - Lata Mangeshkar",
            "url": "https://open.spotify.com/track/0Sm3rEToKnYX3vIjDzrQmn"
        },
        {
            "added_at": null,
            "album": {
                "name": "Love For Sale (Deluxe)",
                "url": "https://open.spotify.com/album/6hBQkPnq5u1BwZncSEDEgs"
            },
            "artists": [
                {
                    "name": "Tony Bennett",
                    "url": "https://open.spotify.com/artist/2lolQgalUvZDfp5vvVtTYV"
                },
                {
                    "name": "Lady Gaga",
                    "url": "https://open.spotify.com/artist/1HY2Jd0NmPuamShAr6KMms"
                }
            ],
            "duration_ms": 213960,
            "name": "I Get A Kick Out Of You",
            "url": "https://open.spotify.com/track/6tANJIaIQAFhMxgnafAZd2"
        },
        {
            "added_at": null,
            "album": {
                "name": "Sailaab",
                "url": "https://open.spotify.com/album/5X8nUjRXgVAlEjE1Oosrvw"
            },
            "artists": [
                {
                    "name": "Anupama",
                    "url": "https://open.spotify.com/artist/1mMKKbLFrIqfOzLqFuGBRt"
                }
            ],
            "duration_ms": 487893,
            "name": "Uljhi Hai Yeh Kis Jaal Mein Tu - Humko Aajkal Hai Intezaar",
            "url": "https://open.spotify.com/track/6Ty2PftKTdV0dkIILRUnRz"
        },
        {
            "added_at": null,
            "album": {
                "name": "Kala Pani",
                "url": "https://open.spotify.com/album/7mJh1ocWFwnqzNNtHzhzVo"
            },
            "artists": [
                {
                    "name": "Asha Bhosle",
                    "url": "https://open.spotify.com/artist/5as8A4G47Ohu9NSWs3Je8U"
                },
                {
                    "name": "Mohammed Rafi",
                    "url": "https://open.spotify.com/artist/0gXDpqwYNDODn7fB0RDN8J"
                },
                {
                    "name": "S. D. Burman",
                    "url": "https://open.spotify.com/artist/4vMKEXQ4cU5hb2BL4omVrT"
                }
            ],
            "duration_ms": 207733,
            "name": "Achha Ji Main Haari Chalo",
            "url": "https://open.spotify.com/track/5ceKyCGIpjceDJhOT9pE7r"
        },
        {
            "added_at": null,
            "album": {
                "name": "Porgy And Bess",
                "url": "https://open.spotify.com/album/1vvnTmmNWnGmqvVFjVIINf"
            },
            "artists": [
                {
                    "name": "Ella Fitzgerald",
                    "url": "https://open.spotify.com/artist/5V0MlUE1Bft0mbLlND7FJz"
                }
            ],
            "duration_ms": 119666,
            "name": "What You Want Wid Bess?",
            "url": "https://open.spotify.com/track/3lo6WG0mdesJZGdRCVPF9p"
        },
        {
            "added_at": null,
            "album": {
                "name": "Dharti Kahe Pukar Ke",
                "url": "https://open.spotify.com/album/0GpJlpUGfLRNuQipA70ysj"
            },
            "artists": [
                {
                    "name": "Lata Mangeshkar",
                    "url": "https://open.spotify.com/artist/61JrslREXq98hurYL2hYoc"
                },
                {
                    "name": "Mukesh",
                    "url": "https://open.spotify.com/artist/4etv0ut4ws0GbXBtolzf5e"
                },
                {
                    "name": "Laxmikant–Pyarelal",
                    "url": "https://open.spotify.com/artist/3yS84AjNFqhmuJlIXy7sax"
                }
            ],
            "duration_ms": 326912,
            "name": "Je Hum Tum Chori Se",
            "url": "https://open.spotify.com/track/3DaK9NznMax9b45HJQ7jVt"
        },
        {
            "added_at": null,
            "album": {
                "name": "Morning Bhajans & Chants",
                "url": "https://open.spotify.com/album/3RtCsB8bv7G8O9SDsyVYCe"
            },
            "artists": [
                {
                    "name": "Suresh Wadkar",
                    "url": "https://open.spotify.com/artist/0w4e7HVbqAHFPN6VkIlvhe"
                },
                {
                    "name": "Lalitya Munshaw",
                    "url": "https://open.spotify.com/artist/3e23DvNuM4Z78nPsX8P1D9"
                }
            ],
            "duration_ms": 247805,
            "name": "Gayatri Mantra",
            "url": "https://open.spotify.com/track/4ui0KLMvGoNfFCP4hWuPh3"
        },
        {
            "added_at": null,
            "album": {
                "name": "Lofi Hindi Hits - Vol 1",
                "url": "https://open.spotify.com/album/4M8wEbGwomPzxhwYFGNlZt"
            },
            "artists": [
                {
                    "name": "Kishore Kumar",
                    "url": "https://open.spotify.com/artist/0GF4shudTAFv8ak9eWdd4Y"
                },
                {
                    "name": "Deepanshu Ruhela",
                    "url": "https://open.spotify.com/artist/5dvCHAlgZZBuYuRdSm3dQE"
                }
            ],
            "duration_ms": 128966,
            "name": "Ek Ladki Bheegi Bhaagi Si - Lofi Reverb",
            "url": "https://open.spotify.com/track/2CbA2yYtaIVzURJdlomehA"
        },
        {
            "added_at": null,
            "album": {
                "name": "Estúpido Cupido",
                "url": "https://open.spotify.com/album/5GXsLvttz4MZ1mX0U64Ph3"
            },
            "artists": [
                {
                    "name": "Celly Campello",
                    "url": "https://open.spotify.com/artist/1aPJLlO6MUhUBc2swwz9uW"
                }
            ],
            "duration_ms": 130199,
            "name": "Estúpido Cupido",
            "url": "https://open.spotify.com/track/7AHcq1TTLsgbnspP1TsP9U"
        },
        {
            "added_at": null,
            "album": {
                "name": "New York Jazz",
                "url": "https://open.spotify.com/album/5iQMDqjUmF9ZY1sLsK5Vmm"
            },
            "artists": [
                {
                    "name": "Sonny Stitt",
                    "url": "https://open.spotify.com/artist/217b0uqAzsOOhGcnoANZqj"
                }
            ],
            "duration_ms": 291840,
            "name": "Alone Together",
            "url": "https://open.spotify.com/track/7lApnj6eswDJvT8mqGrut6"
        },
        {
            "added_at": null,
            "album": {
                "name": "Aah",
                "url": "https://open.spotify.com/album/3hAhQMdtUXYATD1mf4Qoc3"
            },
            "artists": [
                {
                    "name": "Lata Mangeshkar",
                    "url": "https://open.spotify.com/artist/61JrslREXq98hurYL2hYoc"
                },
                {
                    "name": "Mukesh",
                    "url": "https://open.spotify.com/artist/4etv0ut4ws0GbXBtolzf5e"
                }
            ],
            "duration_ms": 219713,
            "name": "Jane Na Nazar Pehchane Jigar",
            "url": "https://open.spotify.com/track/1cpaDNciPGlC39qPs4RkMU"
        },
        {
            "added_at": null,
            "album": {
                "name": "Love For Sale (Deluxe)",
                "url": "https://open.spotify.com/album/6hBQkPnq5u1BwZncSEDEgs"
            },
            "artists": [
                {
                    "name": "Tony Bennett",
                    "url": "https://open.spotify.com/artist/2lolQgalUvZDfp5vvVtTYV"
                },
                {
                    "name": "Lady Gaga",
                    "url": "https://open.spotify.com/artist/1HY2Jd0NmPuamShAr6KMms"
                }
            ],
            "duration_ms": 220786,
            "name": "Love For Sale",
            "url": "https://open.spotify.com/track/4biVNJdcVpAljZjpiO9B4Z"
        },
        {
            "added_at": null,
            "album": {
                "name": "Helen Merrill With Strings",
                "url": "https://open.spotify.com/album/1ZCXk8phZLNQSpOOMhIbWG"
            },
            "artists": [
                {
                    "name": "Helen Merrill",
                    "url": "https://open.spotify.com/artist/4JHlHSUko0ivu6fXYT8J2q"
                }
            ],
            "duration_ms": 187266,
            "name": "Anything Goes",
            "url": "https://open.spotify.com/track/7G7aecTWvlnJoLUJi7tn7f"
        },
        {
            "added_at": null,
            "album": {
                "name": "Mukesh Ki Barfi",
                "url": "https://open.spotify.com/album/30AnFi0y2n2KZIHMzYhSWX"
            },
            "artists": [
                {
                    "name": "Mukesh",
                    "url": "https://open.spotify.com/artist/4etv0ut4ws0GbXBtolzf5e"
                }
            ],
            "duration_ms": 269333,
            "name": "Kisi Ki Muskurahaton Pe",
            "url": "https://open.spotify.com/track/7rkkhMxGDlfpHtV9Y9bKsC"
        },
        {
            "added_at": null,
            "album": {
                "name": "Sadabahar Sangeetkar - Pandit Yashwant",
                "url": "https://open.spotify.com/album/6USiN8CQsoRkRvQ5LPeW2w"
            },
            "artists": [
                {
                    "name": "Arun Date",
                    "url": "https://open.spotify.com/artist/51The0zPgkV0D8mQYgCehn"
                }
            ],
            "duration_ms": 351520,
            "name": "Bhatukalichya Khela Madhali Raja Anik Rani",
            "url": "https://open.spotify.com/track/3YLY1wSIyd0R3zHNavEWAF"
        },
        {
            "added_at": null,
            "album": {
                "name": "Albela",
                "url": "https://open.spotify.com/album/7oVW9nSSdemfWryi2ZXuxn"
            },
            "artists": [
                {
                    "name": "C. Ramchandra",
                    "url": "https://open.spotify.com/artist/4tuzg2QDbDF6ytPrszs4q1"
                },
                {
                    "name": "Lata Mangeshkar",
                    "url": "https://open.spotify.com/artist/61JrslREXq98hurYL2hYoc"
                }
            ],
            "duration_ms": 227525,
            "name": "Dheere Se Aaja Ri Ankhiyan Mein",
            "url": "https://open.spotify.com/track/1s3MPs2lEBgIDMyxwMHF2L"
        },
        {
            "added_at": null,
            "album": {
                "name": "Chori Chori",
                "url": "https://open.spotify.com/album/0POb5F8yL6bRxZNw50CxWl"
            },
            "artists": [
                {
                    "name": "Lata Mangeshkar",
                    "url": "https://open.spotify.com/artist/61JrslREXq98hurYL2hYoc"
                },
                {
                    "name": "Manna Dey",
                    "url": "https://open.spotify.com/artist/4kcoiVXIxvUoLUoHY1vJYU"
                }
            ],
            "duration_ms": 245243,
            "name": "Jahan Main Jati Hoon",
            "url": "https://open.spotify.com/track/6icfkrLmh44XX8zwnIgBV2"
        },
        {
            "added_at": null,
            "album": {
                "name": "Lee Konitz Meets Jimmy Giuffre",
                "url": "https://open.spotify.com/album/4RpZEpHc5YqVOMmxBy3zAs"
            },
            "artists": [
                {
                    "name": "Lee Konitz",
                    "url": "https://open.spotify.com/artist/4YNvbaOaqp5pzC5US5t48k"
                },
                {
                    "name": "Jimmy Giuffre",
                    "url": "https://open.spotify.com/artist/4RncsrNJ1GDGsFBIxI76L6"
                }
            ],
            "duration_ms": 216360,
            "name": "Someone To Watch Over Me",
            "url": "https://open.spotify.com/track/3Gcpi1CwKoQtc8B3H2ZOIX"
        },
        {
            "added_at": null,
            "album": {
                "name": "Ja Ja Ja Bewafa - Heartlock Mix",
                "url": "https://open.spotify.com/album/5Ex9iaaRldqA9h8PgW1NwF"
            },
            "artists": [
                {
                    "name": "Geeta Dutt",
                    "url": "https://open.spotify.com/artist/0QsbYX8XslSSUcztc6u4pO"
                },
                {
                    "name": "Heartlock",
                    "url": "https://open.spotify.com/artist/0XqW9UITIzCIQ4CurIcgwz"
                }
            ],
            "duration_ms": 154173,
            "name": "Ja Ja Ja Bewafa - Heartlock Mix",
            "url": "https://open.spotify.com/track/7DSQvceVQaLDlztMIuQP3Z"
        },
        {
            "added_at": null,
            "album": {
                "name": "Seven Brides For Seven Brothers (Original Motion Picture Soundtrack) [Deluxe Version]",
                "url": "https://open.spotify.com/album/5Je84wV7yIzjOOVWt4XOlP"
            },
            "artists": [
                {
                    "name": "Jane Powell",
                    "url": "https://open.spotify.com/artist/66evJDOWrOPaGFd4hVtCWN"
                },
                {
                    "name": "Virginia Gibson",
                    "url": "https://open.spotify.com/artist/7lHrJQFuW61otASPK7pA3m"
                },
                {
                    "name": "Barbara Ames",
                    "url": "https://open.spotify.com/artist/4SmI3aRM7H0vtjHhqxEKIO"
                },
                {
                    "name": "Betty Allan",
                    "url": "https://open.spotify.com/artist/1SqKGl56S5Jz7IdKBZTv9X"
                },
                {
                    "name": "Betty Noyes",
                    "url": "https://open.spotify.com/artist/3mLYVpwZgpKUH88QeyIkiG"
                },
                {
                    "name": "Marie Vernon",
                    "url": "https://open.spotify.com/artist/1ClwgQJRWgESkZBfsbEuSJ"
                }
            ],
            "duration_ms": 102866,
            "name": "June Bride - (Reprise)",
            "url": "https://open.spotify.com/track/6XnDHJnONMVM3lwWxJi0dh"
        },
        {
            "added_at": null,
            "album": {
                "name": "Lofi Hindi Hits - Vol 3",
                "url": "https://open.spotify.com/album/2wjrBPLqSQvlan4z9aiOAX"
            },
            "artists": [
                {
                    "name": "Mukesh",
                    "url": "https://open.spotify.com/artist/4etv0ut4ws0GbXBtolzf5e"
                },
                {
                    "name": "The Keychangers",
                    "url": "https://open.spotify.com/artist/5HnE0vK2ZcVTpNJjecfJUV"
                }
            ],
            "duration_ms": 179219,
            "name": "Main Pal Do Pal Ka Shayar Hoon - LOFI Hindi Mix",
            "url": "https://open.spotify.com/track/3FT6896k2JmeND7B5XNrGr"
        },
        {
            "added_at": null,
            "album": {
                "name": "P.Susheela - The All Rounder",
                "url": "https://open.spotify.com/album/6ge3WjOXxMygrcj5QbNfIX"
            },
            "artists": [
                {
                    "name": "P. Susheela",
                    "url": "https://open.spotify.com/artist/0aFGod7DM6b3O5l1AmvFwK"
                }
            ],
            "duration_ms": 208546,
            "name": "Love Birds",
            "url": "https://open.spotify.com/track/1x2JJbrZQHwVoUpLS6nZNZ"
        },
        {
            "added_at": null,
            "album": {
                "name": "Ella Fitzgerald Sings The Irving Berlin Song Book",
                "url": "https://open.spotify.com/album/2hK70fCNOlYgTg0sQMzPbj"
            },
            "artists": [
                {
                    "name": "Ella Fitzgerald",
                    "url": "https://open.spotify.com/artist/5V0MlUE1Bft0mbLlND7FJz"
                },
                {
                    "name": "Paul Weston And His Orchestra",
                    "url": "https://open.spotify.com/artist/3EVyH5tLgdq62aXTdKfzey"
                }
            ],
            "duration_ms": 148266,
            "name": "It's A Lovely Day Today",
            "url": "https://open.spotify.com/track/5BLr7EEgi2JdKbMbYjFXas"
        },
        {
            "added_at": null,
            "album": {
                "name": "Patthar Ke Sanam",
                "url": "https://open.spotify.com/album/20EMWYF7Yb2uPtUNfumNOt"
            },
            "artists": [
                {
                    "name": "Mohammed Rafi",
                    "url": "https://open.spotify.com/artist/0gXDpqwYNDODn7fB0RDN8J"
                },
                {
                    "name": "Laxmikant–Pyarelal",
                    "url": "https://open.spotify.com/artist/3yS84AjNFqhmuJlIXy7sax"
                }
            ],
            "duration_ms": 297880,
            "name": "Patthar Ke Sanam",
            "url": "https://open.spotify.com/track/6zs80WifMPHbn3hqlItbzI"
        },
        {
            "added_at": null,
            "album": {
                "name": "Seema",
                "url": "https://open.spotify.com/album/0lPBUky2bkMWO8ZCTqJPHJ"
            },
            "artists": [
                {
                    "name": "Manna Dey",
                    "url": "https://open.spotify.com/artist/4kcoiVXIxvUoLUoHY1vJYU"
                }
            ],
            "duration_ms": 266640,
            "name": "Tu Pyar Ka Sagar Hai",
            "url": "https://open.spotify.com/track/6N9SM1Hwe5cTiPl8KxEfDl"
        },
        {
            "added_at": null,
            "album": {
                "name": "Diamonds Forever - Lata Mangeshkar",
                "url": "https://open.spotify.com/album/7cmbUR0oPLKzrP6j6303Ad"
            },
            "artists": [
                {
                    "name": "Lata Mangeshkar",
                    "url": "https://open.spotify.com/artist/61JrslREXq98hurYL2hYoc"
                },
                {
                    "name": "Kishore Kumar",
                    "url": "https://open.spotify.com/artist/0GF4shudTAFv8ak9eWdd4Y"
                }
            ],
            "duration_ms": 302400,
            "name": "Tere Chehre Se Nazar Nahin (From \"Kabhi Kabhie\")",
            "url": "https://open.spotify.com/track/3bC0b9P6P7zJZ4yHalGjvV"
        },
        {
            "added_at": null,
            "album": {
                "name": "Presenting Anne Shelton",
                "url": "https://open.spotify.com/album/7tlPntHo81jKxk9vXXGKDc"
            },
            "artists": [
                {
                    "name": "Anne Shelton",
                    "url": "https://open.spotify.com/artist/1Ug1gaXH8V5vrIHNyOTXrh"
                }
            ],
            "duration_ms": 177693,
            "name": "Lay Down Your Arms",
            "url": "https://open.spotify.com/track/5hINyxdKUMIF7FqcreAHwF"
        },
        {
            "added_at": null,
            "album": {
                "name": "Born To Be Blue",
                "url": "https://open.spotify.com/album/6vDO6c6V3hYq3KA2psLsZv"
            },
            "artists": [
                {
                    "name": "Beverly Kenney",
                    "url": "https://open.spotify.com/artist/65AXHPhvpKkrCIlk5BuUQT"
                }
            ],
            "duration_ms": 211906,
            "name": "Born To Be Blue",
            "url": "https://open.spotify.com/track/0zjHHk5Lqrf3j1ZpevLcJl"
        },
        {
            "added_at": null,
            "album": {
                "name": "Mukesh Ki Barfi",
                "url": "https://open.spotify.com/album/30AnFi0y2n2KZIHMzYhSWX"
            },
            "artists": [
                {
                    "name": "Mukesh",
                    "url": "https://open.spotify.com/artist/4etv0ut4ws0GbXBtolzf5e"
                }
            ],
            "duration_ms": 338453,
            "name": "Ek Din Bik Jayega Mati Ke Mol (Happy)",
            "url": "https://open.spotify.com/track/4McIJNtDqf4Vo0v0TFQgAa"
        },
        {
            "added_at": null,
            "album": {
                "name": "Assum Preto",
                "url": "https://open.spotify.com/album/6DlI1E7qdmUNZ5X7wj97fG"
            },
            "artists": [
                {
                    "name": "Marcela Brandão",
                    "url": "https://open.spotify.com/artist/4YihvchpM0vU5a2ZoTdyak"
                }
            ],
            "duration_ms": 159813,
            "name": "Assum Preto",
            "url": "https://open.spotify.com/track/5RU97jQPEFEbwA2BMknw8N"
        },
        {
            "added_at": null,
            "album": {
                "name": "Remembering Lata Didi - Hindi",
                "url": "https://open.spotify.com/album/4g8S5lSNMOADleK1x0op0L"
            },
            "artists": [
                {
                    "name": "Lata Mangeshkar",
                    "url": "https://open.spotify.com/artist/61JrslREXq98hurYL2hYoc"
                }
            ],
            "duration_ms": 346480,
            "name": "Sheesha Ho Ya Dil Ho",
            "url": "https://open.spotify.com/track/2xKbWOCzAdOGi3sP3kG1JB"
        },
        {
            "added_at": null,
            "album": {
                "name": "Ella Fitzgerald Sings The Irving Berlin Song Book",
                "url": "https://open.spotify.com/album/2hK70fCNOlYgTg0sQMzPbj"
            },
            "artists": [
                {
                    "name": "Ella Fitzgerald",
                    "url": "https://open.spotify.com/artist/5V0MlUE1Bft0mbLlND7FJz"
                },
                {
                    "name": "Paul Weston And His Orchestra",
                    "url": "https://open.spotify.com/artist/3EVyH5tLgdq62aXTdKfzey"
                }
            ],
            "duration_ms": 226613,
            "name": "You Can Have Him",
            "url": "https://open.spotify.com/track/1FIkhPVchSeLTinKQcC5tV"
        },
        {
            "added_at": null,
            "album": {
                "name": "Love Is Blue",
                "url": "https://open.spotify.com/album/4q9ot78mrbt8U5WEhzrzZa"
            },
            "artists": [
                {
                    "name": "Paul Mauriat",
                    "url": "https://open.spotify.com/artist/5Oj26LEf8jdgR2woWEjlhi"
                }
            ],
            "duration_ms": 157493,
            "name": "Love Is Blue",
            "url": "https://open.spotify.com/track/1PlZt5i69FgDl45KbHlLzr"
        },
        {
            "added_at": null,
            "album": {
                "name": "Things Are Swingin'",
                "url": "https://open.spotify.com/album/0puYTmfXiL5UZLyl33nXKT"
            },
            "artists": [
                {
                    "name": "Peggy Lee",
                    "url": "https://open.spotify.com/artist/602DnpaSXJB4b9DZrvxbDc"
                }
            ],
            "duration_ms": 127800,
            "name": "Alone Together",
            "url": "https://open.spotify.com/track/47xU4Sm1RWZgRgugWPFxzz"
        },
        {
            "added_at": null,
            "album": {
                "name": "The Magic Of Sarah Vaughan",
                "url": "https://open.spotify.com/album/2hTjOrY0sgLWBtvkxb1pcF"
            },
            "artists": [
                {
                    "name": "Sarah Vaughan",
                    "url": "https://open.spotify.com/artist/1bgyxtWjZwA5PQlDsvs9b8"
                }
            ],
            "duration_ms": 146360,
            "name": "Broken Hearted Melody",
            "url": "https://open.spotify.com/track/43zIzwzVqI51alZlyKbKi4"
        },
        {
            "added_at": null,
            "album": {
                "name": "Fever",
                "url": "https://open.spotify.com/album/6F2WrE5RSUbOZyFJNbMeUn"
            },
            "artists": [
                {
                    "name": "Alexander Rybak",
                    "url": "https://open.spotify.com/artist/3LLNDXrxL4uxXtnUJS5XWM"
                },
                {
                    "name": "D'Dorian",
                    "url": "https://open.spotify.com/artist/1hNV45JXomKPKDp1Fsp9vl"
                }
            ],
            "duration_ms": 186012,
            "name": "Fever",
            "url": "https://open.spotify.com/track/4DeLgHoZs34j9p1n62YBRC"
        },
        {
            "added_at": null,
            "album": {
                "name": "Seven Brides For Seven Brothers (Original Motion Picture Soundtrack) [Deluxe Version]",
                "url": "https://open.spotify.com/album/5Je84wV7yIzjOOVWt4XOlP"
            },
            "artists": [
                {
                    "name": "Jane Powell",
                    "url": "https://open.spotify.com/artist/66evJDOWrOPaGFd4hVtCWN"
                },
                {
                    "name": "Tommy Rall",
                    "url": "https://open.spotify.com/artist/4exqWKcyNuiYShlje6vBx6"
                },
                {
                    "name": "Russ Tamblyn",
                    "url": "https://open.spotify.com/artist/0Z1NWGEF6ULtkwnSemOBRF"
                },
                {
                    "name": "Marc Platt",
                    "url": "https://open.spotify.com/artist/1EVlrtfub8kYV9Ha9ZnJ7w"
                },
                {
                    "name": "Matt Mattox",
                    "url": "https://open.spotify.com/artist/0xedN9koJfxYnwMUr70DWK"
                },
                {
                    "name": "Jeff Richards",
                    "url": "https://open.spotify.com/artist/4d3Bll45Lx5ewRqzDtO4UE"
                },
                {
                    "name": "Jacques D'Amboise",
                    "url": "https://open.spotify.com/artist/38eM0Hx2YbPUFxEfITochC"
                },
                {
                    "name": "Howard Hudson",
                    "url": "https://open.spotify.com/artist/0CGswJQ9bzq8CSaOzEfndy"
                },
                {
                    "name": "Gene Lanham",
                    "url": "https://open.spotify.com/artist/1PJishfEPBLlR0HObzHsoh"
                },
                {
                    "name": "Robert Wacker",
                    "url": "https://open.spotify.com/artist/40taT1W0mKmsrsM2ZOK90T"
                }
            ],
            "duration_ms": 215493,
            "name": "Goin' Co'tin'",
            "url": "https://open.spotify.com/track/6iN8azvr6WZJj6IkDqlYDb"
        },
        {
            "added_at": null,
            "album": {
                "name": "Chalti Ka Naam Gaadi",
                "url": "https://open.spotify.com/album/6fDgdTncQer8TPTu8T7snN"
            },
            "artists": [
                {
                    "name": "Asha Bhosle",
                    "url": "https://open.spotify.com/artist/5as8A4G47Ohu9NSWs3Je8U"
                },
                {
                    "name": "Kishore Kumar",
                    "url": "https://open.spotify.com/artist/0GF4shudTAFv8ak9eWdd4Y"
                },
                {
                    "name": "S. D. Burman",
                    "url": "https://open.spotify.com/artist/4vMKEXQ4cU5hb2BL4omVrT"
                }
            ],
            "duration_ms": 264706,
            "name": "Haal Kaisa Hai Janab Ka",
            "url": "https://open.spotify.com/track/3uvvmqUNKEzZtZWOQrQqq0"
        },
        {
            "added_at": null,
            "album": {
                "name": "Diamonds Forever - Lata Mangeshkar",
                "url": "https://open.spotify.com/album/7cmbUR0oPLKzrP6j6303Ad"
            },
            "artists": [
                {
                    "name": "Lata Mangeshkar",
                    "url": "https://open.spotify.com/artist/61JrslREXq98hurYL2hYoc"
                },
                {
                    "name": "Kishore Kumar",
                    "url": "https://open.spotify.com/artist/0GF4shudTAFv8ak9eWdd4Y"
                }
            ],
            "duration_ms": 252360,
            "name": "Tum Aa Gaye Ho Noor Aa Gaya (From \"Aandhi\")",
            "url": "https://open.spotify.com/track/46vtbOdgiQHYQgBRwn1sYr"
        },
        {
            "added_at": null,
            "album": {
                "name": "Aasha",
                "url": "https://open.spotify.com/album/6WevJfc020tYLDzdDHtqWh"
            },
            "artists": [
                {
                    "name": "Mohammed Rafi",
                    "url": "https://open.spotify.com/artist/0gXDpqwYNDODn7fB0RDN8J"
                },
                {
                    "name": "Laxmikant–Pyarelal",
                    "url": "https://open.spotify.com/artist/3yS84AjNFqhmuJlIXy7sax"
                }
            ],
            "duration_ms": 325826,
            "name": "Jane Ham Sadak Ke Logon Se",
            "url": "https://open.spotify.com/track/4fE3tfQkbLgErdNKOHpfVB"
        },
        {
            "added_at": null,
            "album": {
                "name": "Anandha Jodhi",
                "url": "https://open.spotify.com/album/2HX4ESYBCuqoJmbJG75ipo"
            },
            "artists": [
                {
                    "name": "P. Susheela",
                    "url": "https://open.spotify.com/artist/0aFGod7DM6b3O5l1AmvFwK"
                }
            ],
            "duration_ms": 277520,
            "name": "Ninaikka Therintha",
            "url": "https://open.spotify.com/track/0V1hxNic8zcY27AZujnynr"
        },
        {
            "added_at": null,
            "album": {
                "name": "Ella Fitzgerald Sings The Cole Porter Song Book",
                "url": "https://open.spotify.com/album/6nOxyYuddsKmHYRQccKSjM"
            },
            "artists": [
                {
                    "name": "Ella Fitzgerald",
                    "url": "https://open.spotify.com/artist/5V0MlUE1Bft0mbLlND7FJz"
                }
            ],
            "duration_ms": 104360,
            "name": "All Of You",
            "url": "https://open.spotify.com/track/65O89M7GMB8pA88VyxxJm7"
        },
        {
            "added_at": null,
            "album": {
                "name": "Verve Remixed: The First Ladies",
                "url": "https://open.spotify.com/album/19JygptHJkK4XkjAcgchxg"
            },
            "artists": [
                {
                    "name": "Astrud Gilberto",
                    "url": "https://open.spotify.com/artist/5rX2c1zow6hCph8PnnU3kF"
                },
                {
                    "name": "Kaskade",
                    "url": "https://open.spotify.com/artist/6TQj5BFPooTa08A7pk8AQ1"
                }
            ],
            "duration_ms": 344520,
            "name": "Fly Me To The Moon - Kaskade Remix",
            "url": "https://open.spotify.com/track/1nBpcLI7wkyCYBVvffDByl"
        },
        {
            "added_at": null,
            "album": {
                "name": "Doris Day with Love",
                "url": "https://open.spotify.com/album/1TNkI3ngZcgUqqYJGEk23l"
            },
            "artists": [
                {
                    "name": "Doris Day",
                    "url": "https://open.spotify.com/artist/3ESG6pj6a0LvUKklENalT6"
                },
                {
                    "name": "The Sentimental Pops Orchestra",
                    "url": "https://open.spotify.com/artist/1zkne10EzsG4m0bD80fFkw"
                }
            ],
            "duration_ms": 138880,
            "name": "Singin' in the Rain",
            "url": "https://open.spotify.com/track/6d4dlfT9TRoAatdAX8syth"
        },
        {
            "added_at": null,
            "album": {
                "name": "Dancing Classics with Frank Chacksfield & His Orchestra (Remastered)",
                "url": "https://open.spotify.com/album/6eT2Ga0vQo9YIpuduvKXAe"
            },
            "artists": [
                {
                    "name": "Frank Chacksfield",
                    "url": "https://open.spotify.com/artist/556bh5qJfhSUkjTluTTyMF"
                },
                {
                    "name": "Frank Chacksfield Orchestra",
                    "url": "https://open.spotify.com/artist/4p9uMiH2i6QPYGXx3WmpVi"
                },
                {
                    "name": "Frank Chacksfield & His Orchestra",
                    "url": "https://open.spotify.com/artist/01zQA436fdUqmEWvljtzxr"
                }
            ],
            "duration_ms": 207040,
            "name": "We're All Alone - Remastered",
            "url": "https://open.spotify.com/track/53xGtcOZJsbHASlNoNtn96"
        },
        {
            "added_at": null,
            "album": {
                "name": "Rockin' With Danny And The Juniors (Expanded Edition)",
                "url": "https://open.spotify.com/album/0AL8t9Dy1L9nf1ZnBlLeLq"
            },
            "artists": [
                {
                    "name": "Danny & The Juniors",
                    "url": "https://open.spotify.com/artist/6Ahm6X9wSKXitavOvu0XzY"
                }
            ],
            "duration_ms": 150866,
            "name": "At The Hop",
            "url": "https://open.spotify.com/track/4LcrHUkRmXG3c0YD5VYutn"
        }
    ],
    "unique_name": "50s Mix",
    "url": "https://open.spotify.com/playlist/37i9dQZF1EQqMLgxRRiCOd"
}
